README.rst
setup.py
shenjian/__init__.py
shenjian/api.py
shenjian/host_type.py
shenjian/proxy_type.py
shenjian.egg-info/PKG-INFO
shenjian.egg-info/SOURCES.txt
shenjian.egg-info/dependency_links.txt
shenjian.egg-info/requires.txt
shenjian.egg-info/top_level.txt