Metadata-Version: 1.0
Name: shenjian
Version: 1.2
Summary: shenjian rest sdk
Home-page: http://www.shenjian.io
Author: UNKNOWN
Author-email: UNKNOWN
License: UNKNOWN
Platform: UNKNOWN
